[
  {
    "titolo": "Offerta Amazon",
    "link": "",
    "img": "https://api.telegram.org/file/bot8085845485:AAGi5BcEENkGSkQg00YhHQyl3bkBXXDUO-o/photos/file_1666.jpg",
    "telegram_link": "https://t.me/c/1464832267/102293"
  },
  {
    "titolo": "Offerta Amazon",
    "link": "",
    "img": "https://api.telegram.org/file/bot8085845485:AAGi5BcEENkGSkQg00YhHQyl3bkBXXDUO-o/photos/file_1665.jpg",
    "telegram_link": "https://t.me/c/1464832267/102292"
  },
  {
    "titolo": "Offerta Amazon",
    "link": "",
    "img": "https://api.telegram.org/file/bot8085845485:AAGi5BcEENkGSkQg00YhHQyl3bkBXXDUO-o/photos/file_1664.jpg",
    "telegram_link": "https://t.me/c/1464832267/102291"
  },
  {
    "titolo": "Offerta Amazon",
    "link": "",
    "img": "https://api.telegram.org/file/bot8085845485:AAGi5BcEENkGSkQg00YhHQyl3bkBXXDUO-o/photos/file_1663.jpg",
    "telegram_link": "https://t.me/c/1464832267/102290"
  },
  {
    "titolo": "Offerta Amazon",
    "link": "",
    "img": "https://api.telegram.org/file/bot8085845485:AAGi5BcEENkGSkQg00YhHQyl3bkBXXDUO-o/photos/file_1662.jpg",
    "telegram_link": "https://t.me/c/1464832267/102289"
  },
  {
    "titolo": "Offerta Amazon",
    "link": "",
    "img": "https://api.telegram.org/file/bot8085845485:AAGi5BcEENkGSkQg00YhHQyl3bkBXXDUO-o/photos/file_1661.jpg",
    "telegram_link": "https://t.me/c/1464832267/102288"
  },
  {
    "titolo": "Offerta Amazon",
    "link": "",
    "img": "https://api.telegram.org/file/bot8085845485:AAGi5BcEENkGSkQg00YhHQyl3bkBXXDUO-o/photos/file_1660.jpg",
    "telegram_link": "https://t.me/c/1464832267/102287"
  },
  {
    "titolo": "Offerta Amazon",
    "link": "",
    "img": "https://api.telegram.org/file/bot8085845485:AAGi5BcEENkGSkQg00YhHQyl3bkBXXDUO-o/photos/file_1659.jpg",
    "telegram_link": "https://t.me/c/1464832267/102286"
  },
  {
    "titolo": "Offerta Amazon",
    "link": "",
    "img": "https://api.telegram.org/file/bot8085845485:AAGi5BcEENkGSkQg00YhHQyl3bkBXXDUO-o/photos/file_1658.jpg",
    "telegram_link": "https://t.me/c/1464832267/102285"
  },
  {
    "titolo": "Offerta Amazon",
    "link": "",
    "img": "https://api.telegram.org/file/bot8085845485:AAGi5BcEENkGSkQg00YhHQyl3bkBXXDUO-o/photos/file_1657.jpg",
    "telegram_link": "https://t.me/c/1464832267/102284"
  },
  {
    "titolo": "Offerta Amazon",
    "link": "",
    "img": "https://api.telegram.org/file/bot8085845485:AAGi5BcEENkGSkQg00YhHQyl3bkBXXDUO-o/photos/file_1656.jpg",
    "telegram_link": "https://t.me/c/1464832267/102283"
  },
  {
    "titolo": "Offerta Amazon",
    "link": "",
    "img": "https://api.telegram.org/file/bot8085845485:AAGi5BcEENkGSkQg00YhHQyl3bkBXXDUO-o/photos/file_1655.jpg",
    "telegram_link": "https://t.me/c/1464832267/102282"
  },
  {
    "titolo": "Offerta Amazon",
    "link": "",
    "img": "https://api.telegram.org/file/bot8085845485:AAGi5BcEENkGSkQg00YhHQyl3bkBXXDUO-o/photos/file_1654.jpg",
    "telegram_link": "https://t.me/c/1464832267/102281"
  },
  {
    "titolo": "Offerta Amazon",
    "link": "",
    "img": "https://api.telegram.org/file/bot8085845485:AAGi5BcEENkGSkQg00YhHQyl3bkBXXDUO-o/photos/file_1653.jpg",
    "telegram_link": "https://t.me/c/1464832267/102280"
  },
  {
    "titolo": "Offerta Amazon",
    "link": "",
    "img": "https://api.telegram.org/file/bot8085845485:AAGi5BcEENkGSkQg00YhHQyl3bkBXXDUO-o/photos/file_1652.jpg",
    "telegram_link": "https://t.me/c/1464832267/102279"
  },
  {
    "titolo": "Offerta Amazon",
    "link": "",
    "img": "https://api.telegram.org/file/bot8085845485:AAGi5BcEENkGSkQg00YhHQyl3bkBXXDUO-o/photos/file_1651.jpg",
    "telegram_link": "https://t.me/c/1464832267/102278"
  },
  {
    "titolo": "Offerta Amazon",
    "link": "",
    "img": "https://api.telegram.org/file/bot8085845485:AAGi5BcEENkGSkQg00YhHQyl3bkBXXDUO-o/photos/file_1650.jpg",
    "telegram_link": "https://t.me/c/1464832267/102277"
  },
  {
    "titolo": "Offerta Amazon",
    "link": "",
    "img": "https://api.telegram.org/file/bot8085845485:AAGi5BcEENkGSkQg00YhHQyl3bkBXXDUO-o/photos/file_1649.jpg",
    "telegram_link": "https://t.me/c/1464832267/102276"
  },
  {
    "titolo": "Offerta Amazon",
    "link": "",
    "img": "https://api.telegram.org/file/bot8085845485:AAGi5BcEENkGSkQg00YhHQyl3bkBXXDUO-o/photos/file_1648.jpg",
    "telegram_link": "https://t.me/c/1464832267/102275"
  },
  {
    "titolo": "Offerta Amazon",
    "link": "",
    "img": "https://api.telegram.org/file/bot8085845485:AAGi5BcEENkGSkQg00YhHQyl3bkBXXDUO-o/photos/file_1647.jpg",
    "telegram_link": "https://t.me/c/1464832267/102274"
  },
  {
    "titolo": "Offerta Amazon",
    "link": "",
    "img": "https://api.telegram.org/file/bot8085845485:AAGi5BcEENkGSkQg00YhHQyl3bkBXXDUO-o/photos/file_1646.jpg",
    "telegram_link": "https://t.me/c/1464832267/102273"
  },
  {
    "titolo": "Offerta Amazon",
    "link": "",
    "img": "https://api.telegram.org/file/bot8085845485:AAGi5BcEENkGSkQg00YhHQyl3bkBXXDUO-o/photos/file_1645.jpg",
    "telegram_link": "https://t.me/c/1464832267/102272"
  },
  {
    "titolo": "Offerta Amazon",
    "link": "",
    "img": "https://api.telegram.org/file/bot8085845485:AAGi5BcEENkGSkQg00YhHQyl3bkBXXDUO-o/photos/file_1644.jpg",
    "telegram_link": "https://t.me/c/1464832267/102271"
  },
  {
    "titolo": "Offerta Amazon",
    "link": "",
    "img": "https://api.telegram.org/file/bot8085845485:AAGi5BcEENkGSkQg00YhHQyl3bkBXXDUO-o/photos/file_1643.jpg",
    "telegram_link": "https://t.me/c/1464832267/102270"
  },
  {
    "titolo": "Offerta Amazon",
    "link": "",
    "img": "https://api.telegram.org/file/bot8085845485:AAGi5BcEENkGSkQg00YhHQyl3bkBXXDUO-o/photos/file_1642.jpg",
    "telegram_link": "https://t.me/c/1464832267/102269"
  },
  {
    "titolo": "Offerta Amazon",
    "link": "",
    "img": "https://api.telegram.org/file/bot8085845485:AAGi5BcEENkGSkQg00YhHQyl3bkBXXDUO-o/photos/file_1641.jpg",
    "telegram_link": "https://t.me/c/1464832267/102268"
  },
  {
    "titolo": "Offerta Amazon",
    "link": "",
    "img": "https://api.telegram.org/file/bot8085845485:AAGi5BcEENkGSkQg00YhHQyl3bkBXXDUO-o/photos/file_1640.jpg",
    "telegram_link": "https://t.me/c/1464832267/102267"
  },
  {
    "titolo": "Offerta Amazon",
    "link": "",
    "img": "https://api.telegram.org/file/bot8085845485:AAGi5BcEENkGSkQg00YhHQyl3bkBXXDUO-o/photos/file_1639.jpg",
    "telegram_link": "https://t.me/c/1464832267/102266"
  },
  {
    "titolo": "Offerta Amazon",
    "link": "",
    "img": "https://api.telegram.org/file/bot8085845485:AAGi5BcEENkGSkQg00YhHQyl3bkBXXDUO-o/photos/file_1638.jpg",
    "telegram_link": "https://t.me/c/1464832267/102265"
  },
  {
    "titolo": "Offerta Amazon",
    "link": "",
    "img": "https://api.telegram.org/file/bot8085845485:AAGi5BcEENkGSkQg00YhHQyl3bkBXXDUO-o/photos/file_1637.jpg",
    "telegram_link": "https://t.me/c/1464832267/102264"
  }
]