[
  {
    "titolo": "Offerta Amazon",
    "link": "",
    "img": "https://api.telegram.org/file/bot8085845485:AAGi5BcEENkGSkQg00YhHQyl3bkBXXDUO-o/photos/file_334.jpg",
    "telegram_link": "https://t.me/c/1464832267/100698"
  },
  {
    "titolo": "Offerta Amazon",
    "link": "",
    "img": "https://api.telegram.org/file/bot8085845485:AAGi5BcEENkGSkQg00YhHQyl3bkBXXDUO-o/photos/file_333.jpg",
    "telegram_link": "https://t.me/c/1464832267/100697"
  },
  {
    "titolo": "Offerta Amazon",
    "link": "",
    "img": "https://api.telegram.org/file/bot8085845485:AAGi5BcEENkGSkQg00YhHQyl3bkBXXDUO-o/photos/file_332.jpg",
    "telegram_link": "https://t.me/c/1464832267/100696"
  },
  {
    "titolo": "Offerta Amazon",
    "link": "",
    "img": "https://api.telegram.org/file/bot8085845485:AAGi5BcEENkGSkQg00YhHQyl3bkBXXDUO-o/photos/file_331.jpg",
    "telegram_link": "https://t.me/c/1464832267/100695"
  },
  {
    "titolo": "Offerta Amazon",
    "link": "",
    "img": "https://api.telegram.org/file/bot8085845485:AAGi5BcEENkGSkQg00YhHQyl3bkBXXDUO-o/photos/file_330.jpg",
    "telegram_link": "https://t.me/c/1464832267/100694"
  },
  {
    "titolo": "Offerta Amazon",
    "link": "",
    "img": "https://api.telegram.org/file/bot8085845485:AAGi5BcEENkGSkQg00YhHQyl3bkBXXDUO-o/photos/file_329.jpg",
    "telegram_link": "https://t.me/c/1464832267/100693"
  },
  {
    "titolo": "Offerta Amazon",
    "link": "",
    "img": "https://api.telegram.org/file/bot8085845485:AAGi5BcEENkGSkQg00YhHQyl3bkBXXDUO-o/photos/file_328.jpg",
    "telegram_link": "https://t.me/c/1464832267/100692"
  },
  {
    "titolo": "Offerta Amazon",
    "link": "",
    "img": "https://api.telegram.org/file/bot8085845485:AAGi5BcEENkGSkQg00YhHQyl3bkBXXDUO-o/photos/file_327.jpg",
    "telegram_link": "https://t.me/c/1464832267/100691"
  },
  {
    "titolo": "Offerta Amazon",
    "link": "",
    "img": "https://api.telegram.org/file/bot8085845485:AAGi5BcEENkGSkQg00YhHQyl3bkBXXDUO-o/photos/file_326.jpg",
    "telegram_link": "https://t.me/c/1464832267/100690"
  },
  {
    "titolo": "Offerta Amazon",
    "link": "",
    "img": "https://api.telegram.org/file/bot8085845485:AAGi5BcEENkGSkQg00YhHQyl3bkBXXDUO-o/photos/file_325.jpg",
    "telegram_link": "https://t.me/c/1464832267/100689"
  },
  {
    "titolo": "Offerta Amazon",
    "link": "",
    "img": "https://api.telegram.org/file/bot8085845485:AAGi5BcEENkGSkQg00YhHQyl3bkBXXDUO-o/photos/file_324.jpg",
    "telegram_link": "https://t.me/c/1464832267/100688"
  },
  {
    "titolo": "Offerta Amazon",
    "link": "",
    "img": "https://api.telegram.org/file/bot8085845485:AAGi5BcEENkGSkQg00YhHQyl3bkBXXDUO-o/photos/file_323.jpg",
    "telegram_link": "https://t.me/c/1464832267/100687"
  },
  {
    "titolo": "Offerta Amazon",
    "link": "",
    "img": "https://api.telegram.org/file/bot8085845485:AAGi5BcEENkGSkQg00YhHQyl3bkBXXDUO-o/photos/file_322.jpg",
    "telegram_link": "https://t.me/c/1464832267/100686"
  },
  {
    "titolo": "Offerta Amazon",
    "link": "",
    "img": "https://api.telegram.org/file/bot8085845485:AAGi5BcEENkGSkQg00YhHQyl3bkBXXDUO-o/photos/file_321.jpg",
    "telegram_link": "https://t.me/c/1464832267/100685"
  },
  {
    "titolo": "Offerta Amazon",
    "link": "",
    "img": "https://api.telegram.org/file/bot8085845485:AAGi5BcEENkGSkQg00YhHQyl3bkBXXDUO-o/photos/file_320.jpg",
    "telegram_link": "https://t.me/c/1464832267/100684"
  },
  {
    "titolo": "Offerta Amazon",
    "link": "",
    "img": "https://api.telegram.org/file/bot8085845485:AAGi5BcEENkGSkQg00YhHQyl3bkBXXDUO-o/photos/file_319.jpg",
    "telegram_link": "https://t.me/c/1464832267/100683"
  },
  {
    "titolo": "Offerta Amazon",
    "link": "",
    "img": "https://api.telegram.org/file/bot8085845485:AAGi5BcEENkGSkQg00YhHQyl3bkBXXDUO-o/photos/file_318.jpg",
    "telegram_link": "https://t.me/c/1464832267/100682"
  },
  {
    "titolo": "Offerta Amazon",
    "link": "",
    "img": "https://api.telegram.org/file/bot8085845485:AAGi5BcEENkGSkQg00YhHQyl3bkBXXDUO-o/photos/file_317.jpg",
    "telegram_link": "https://t.me/c/1464832267/100681"
  },
  {
    "titolo": "Offerta Amazon",
    "link": "",
    "img": "https://api.telegram.org/file/bot8085845485:AAGi5BcEENkGSkQg00YhHQyl3bkBXXDUO-o/photos/file_316.jpg",
    "telegram_link": "https://t.me/c/1464832267/100680"
  },
  {
    "titolo": "Offerta Amazon",
    "link": "",
    "img": "https://api.telegram.org/file/bot8085845485:AAGi5BcEENkGSkQg00YhHQyl3bkBXXDUO-o/photos/file_315.jpg",
    "telegram_link": "https://t.me/c/1464832267/100679"
  },
  {
    "titolo": "Offerta Amazon",
    "link": "",
    "img": "https://api.telegram.org/file/bot8085845485:AAGi5BcEENkGSkQg00YhHQyl3bkBXXDUO-o/photos/file_314.jpg",
    "telegram_link": "https://t.me/c/1464832267/100678"
  },
  {
    "titolo": "Offerta Amazon",
    "link": "",
    "img": "https://api.telegram.org/file/bot8085845485:AAGi5BcEENkGSkQg00YhHQyl3bkBXXDUO-o/photos/file_313.jpg",
    "telegram_link": "https://t.me/c/1464832267/100677"
  },
  {
    "titolo": "Offerta Amazon",
    "link": "",
    "img": "https://api.telegram.org/file/bot8085845485:AAGi5BcEENkGSkQg00YhHQyl3bkBXXDUO-o/photos/file_312.jpg",
    "telegram_link": "https://t.me/c/1464832267/100676"
  },
  {
    "titolo": "Offerta Amazon",
    "link": "",
    "img": "https://api.telegram.org/file/bot8085845485:AAGi5BcEENkGSkQg00YhHQyl3bkBXXDUO-o/photos/file_311.jpg",
    "telegram_link": "https://t.me/c/1464832267/100675"
  },
  {
    "titolo": "Offerta Amazon",
    "link": "",
    "img": "https://api.telegram.org/file/bot8085845485:AAGi5BcEENkGSkQg00YhHQyl3bkBXXDUO-o/photos/file_310.jpg",
    "telegram_link": "https://t.me/c/1464832267/100674"
  },
  {
    "titolo": "Offerta Amazon",
    "link": "",
    "img": "https://api.telegram.org/file/bot8085845485:AAGi5BcEENkGSkQg00YhHQyl3bkBXXDUO-o/photos/file_309.jpg",
    "telegram_link": "https://t.me/c/1464832267/100673"
  },
  {
    "titolo": "Offerta Amazon",
    "link": "",
    "img": "https://api.telegram.org/file/bot8085845485:AAGi5BcEENkGSkQg00YhHQyl3bkBXXDUO-o/photos/file_308.jpg",
    "telegram_link": "https://t.me/c/1464832267/100672"
  },
  {
    "titolo": "Offerta Amazon",
    "link": "",
    "img": "https://api.telegram.org/file/bot8085845485:AAGi5BcEENkGSkQg00YhHQyl3bkBXXDUO-o/photos/file_307.jpg",
    "telegram_link": "https://t.me/c/1464832267/100671"
  },
  {
    "titolo": "Offerta Amazon",
    "link": "",
    "img": "https://api.telegram.org/file/bot8085845485:AAGi5BcEENkGSkQg00YhHQyl3bkBXXDUO-o/photos/file_306.jpg",
    "telegram_link": "https://t.me/c/1464832267/100670"
  },
  {
    "titolo": "Offerta Amazon",
    "link": "",
    "img": "https://api.telegram.org/file/bot8085845485:AAGi5BcEENkGSkQg00YhHQyl3bkBXXDUO-o/photos/file_305.jpg",
    "telegram_link": "https://t.me/c/1464832267/100669"
  }
]